amberprep/Fill_missing_residues.py
amberprep/__init__.py
amberprep/__main__.py
amberprep/add_caps.py
amberprep/app.py
amberprep/docking.py
amberprep/docking_utils.py
amberprep/structure_preparation.py
amberprep/css/plumed.css
amberprep/css/styles.css
amberprep/html/index.html
amberprep/html/plumed.html
amberprep/js/plumed.js
amberprep/js/plumed_cv_docs.js
amberprep/js/script.js
amberprep-0.1.3.dist-info/licenses/LICENSE
amberprep-0.1.3.dist-info/METADATA
amberprep-0.1.3.dist-info/WHEEL
amberprep-0.1.3.dist-info/entry_points.txt
amberprep-0.1.3.dist-info/top_level.txt
amberprep-0.1.3.dist-info/RECORD
