Metadata-Version: 2.4
Name: amberprep
Version: 0.1.3
Summary: Web-based MD simulation pipeline with AMBER, ESMFold, docking, and PLUMED
Author-email: Hemant Nagar <hn533621@ohio.edu>
License: MIT
Project-URL: Homepage, https://huggingface.co/spaces/hemantn/AmberPrep
Project-URL: Documentation, https://github.com/nagarh/AmberPrep
Project-URL: Repository, https://github.com/nagarh/AmberPrep
Project-URL: Issues, https://github.com/nagarh/AmberPrep/issues
Keywords: molecular-dynamics,amber,md-simulation,protein-structure,esmfold,docking,autodock-vina,plumed,computational-chemistry,bioinformatics
Classifier: Development Status :: 4 - Beta
Classifier: Environment :: Web Environment
Classifier: Framework :: Flask
Classifier: Intended Audience :: Science/Research
Classifier: License :: OSI Approved :: MIT License
Classifier: Operating System :: OS Independent
Classifier: Programming Language :: Python :: 3
Classifier: Programming Language :: Python :: 3.10
Classifier: Programming Language :: Python :: 3.11
Classifier: Programming Language :: Python :: 3.12
Classifier: Topic :: Scientific/Engineering :: Bio-Informatics
Classifier: Topic :: Scientific/Engineering :: Chemistry
Requires-Python: >=3.10
License-File: LICENSE
Requires-Dist: flask==2.3.3
Requires-Dist: flask-cors==4.0.0
Requires-Dist: biopython
Requires-Dist: seaborn
Requires-Dist: mdanalysis
Requires-Dist: gunicorn==21.2.0
Requires-Dist: requests
Requires-Dist: meeko>=0.7.0
Requires-Dist: prody
Requires-Dist: numpy<2.0
Provides-Extra: dev
Requires-Dist: pytest>=7.0.0; extra == "dev"
Requires-Dist: pytest-cov>=4.0.0; extra == "dev"
Requires-Dist: black>=23.0.0; extra == "dev"
Requires-Dist: isort>=5.12.0; extra == "dev"
Requires-Dist: flake8>=6.0.0; extra == "dev"
Dynamic: license-file
